medaprep/__init__.py
medaprep/skim.py
medaprep/visualize.py
medaprep/tests/__init__.py
medaprep/tests/conftest.py
medaprep/tests/test_skim.py
medaprep/tests/test_visualize.py
medaprep-0.1.1.dist-info/LICENSE
medaprep-0.1.1.dist-info/METADATA
medaprep-0.1.1.dist-info/WHEEL
medaprep-0.1.1.dist-info/top_level.txt
medaprep-0.1.1.dist-info/RECORD
