Metadata-Version: 2.1
Name: medaprep
Version: 0.1.1
Home-page: https://github.com/makepath/medaprep
Author: makepath
License: MIT
Platform: any
Requires-Python: >=3.10
License-File: LICENSE
Requires-Dist: bokeh
Requires-Dist: colorcet
Requires-Dist: folium
Requires-Dist: numpy
Requires-Dist: pandas
Requires-Dist: scipy
Requires-Dist: shapely
Requires-Dist: xarray
